cheshire/__init__.py
cheshire/database_analyzer.py
cheshire/db_connectors.py
cheshire/logo.ans
cheshire/logo2.ans
cheshire/main.py
cheshire/map_renderer.py
cheshire/matrix_heatmap.py
cheshire/pie_chart.py
cheshire/tui_mode.py
cheshire/waffle_chart.py
cheshire_sql-0.1.2.dist-info/licenses/LICENSE
cheshire_sql-0.1.2.dist-info/METADATA
cheshire_sql-0.1.2.dist-info/WHEEL
cheshire_sql-0.1.2.dist-info/entry_points.txt
cheshire_sql-0.1.2.dist-info/top_level.txt
cheshire_sql-0.1.2.dist-info/RECORD
