Metadata-Version: 2.4
Name: cheshire-sql
Version: 0.1.2
Summary: Terminal-based SQL visualization tool that transforms query results into beautiful ANSI charts
Home-page: https://github.com/yourusername/cheshire
Author: Cheshire Team
Author-email: Ryan Robitaille <ryan.robitaille@gmail.com>
License: MIT License
Project-URL: Homepage, https://github.com/ryrobes/cheshire
Project-URL: Repository, https://github.com/ryrobes/cheshire
Project-URL: Documentation, https://github.com/ryrobes/cheshire#readme
Project-URL: Bug Reports, https://github.com/ryrobes/cheshire/issues
Keywords: sql,visualization,terminal,charts,database,duckdb,cli
Classifier: Development Status :: 4 - Beta
Classifier: Environment :: Console
Classifier: Intended Audience :: Developers
Classifier: Intended Audience :: System Administrators
Classifier: License :: OSI Approved :: MIT License
Classifier: Operating System :: OS Independent
Classifier: Programming Language :: Python :: 3
Classifier: Programming Language :: Python :: 3.8
Classifier: Programming Language :: Python :: 3.9
Classifier: Programming Language :: Python :: 3.10
Classifier: Programming Language :: Python :: 3.11
Classifier: Programming Language :: Python :: 3.12
Classifier: Topic :: Database
Classifier: Topic :: Scientific/Engineering :: Visualization
Classifier: Topic :: System :: Monitoring
Classifier: Topic :: Utilities
Requires-Python: >=3.8
License-File: LICENSE
Requires-Dist: duckdb>=1.0.0
Requires-Dist: plotext>=5.2.0
Requires-Dist: pyyaml>=6.0
Requires-Dist: click>=8.1.0
Requires-Dist: pyfiglet>=0.8.0
Requires-Dist: textual>=0.47.0
Requires-Dist: rich>=13.0.0
Requires-Dist: clickhouse-driver>=0.2.6
Requires-Dist: termgraph
Provides-Extra: dev
Requires-Dist: pytest>=7.0.0; extra == "dev"
Requires-Dist: pytest-cov>=4.0.0; extra == "dev"
Requires-Dist: black>=22.0.0; extra == "dev"
Requires-Dist: flake8>=5.0.0; extra == "dev"
Requires-Dist: mypy>=1.0.0; extra == "dev"
Dynamic: author
Dynamic: home-page
Dynamic: license-file
Dynamic: requires-python
